AshutoshGupta_101703118_Fill_Missing_Values/__init__.py
AshutoshGupta_101703118_Fill_Missing_Values/missing_values.py
AshutoshGupta_101703118_Fill_Missing_Values-0.1.dist-info/METADATA
AshutoshGupta_101703118_Fill_Missing_Values-0.1.dist-info/WHEEL
AshutoshGupta_101703118_Fill_Missing_Values-0.1.dist-info/top_level.txt
AshutoshGupta_101703118_Fill_Missing_Values-0.1.dist-info/RECORD
