Metadata-Version: 2.1
Name: AshutoshGupta-101703118-Fill-Missing-Values
Version: 0.1
Summary: A small package for filling missing values in the given dataset
Home-page: UNKNOWN
Author: Ashutosh Gupta
Author-email: agupta12_be17@thapar.edu
License: UNKNOWN
Keywords: command-line,Missing values,missing-values
Platform: UNKNOWN
Classifier: Programming Language :: Python :: 3
Classifier: License :: OSI Approved :: MIT License
Classifier: Operating System :: OS Independent
Requires-Python: >=3.6
